[{"s": "binokl-na-aliekspress-kotoryj-daleko", "t": "Как выбрать бинокль на АлиЭкспресс для дальнего наблюдения: гайд 2026", "i": "📱", "c": "elektronika-i-gadzhety"}, {"s": "biznes-litsenziya-na-aliekspress-chto-eto", "t": "Бизнес-лицензия на AliExpress: как оформить и зачем нужна", "i": "💼", "c": "prodavtsam-i-biznes"}, {"s": "biznes-s-aliekspress-chto-prodavat", "t": "Что выгодно продавать с AliExpress: идеи для бизнеса", "i": "💼", "c": "prodavtsam-i-biznes"}, {"s": "biznes-s-kitaem-s-chego-nachat-aliekspress", "t": "Бизнес с Китаем с нуля: старт на AliExpress для новичков", "i": "💼", "c": "prodavtsam-i-biznes"}, {"s": "binokl-kak-vybrat-khoroshij-nedorogoj-na-aliekspress", "t": "Как выбрать бинокль на Алиэкспресс: гид по недорогим моделям", "i": "📱", "c": "elektronika-i-gadzhety"}, {"s": "biznes-s-aliekspress-bez-vlozhenij-s-kem-sotrudnichat", "t": "Бизнес с AliExpress без вложений: с кем сотрудничать и как начать", "i": "💼", "c": "prodavtsam-i-biznes"}, {"s": "biznes-s-aliekspress-s-chego-nachat", "t": "Бизнес с Алиэкспресс: пошаговый старт и поиск поставщиков", "i": "💼", "c": "prodavtsam-i-biznes"}, {"s": "biznes-s-aliekspress-s-chego-nachat-otzyvy", "t": "Бизнес с AliExpress с нуля: пошаговый старт и отзывы", "i": "💼", "c": "prodavtsam-i-biznes"}, {"s": "birthday-aliexpress-chto-eto", "t": "Birthday AliExpress: что это, где найти и как активировать", "i": "🏷️", "c": "kupony-i-skidki"}, {"s": "bizhuteriya-s-aliekspress-iz-chego", "t": "Из чего сделана бижутерия на Алиэкспресс: полный гид", "i": "📏", "c": "razmery-i-vybor"}, {"s": "bizhuteriya-s-aliekspress-kotoraya-ne-temneet", "t": "Бижутерия с АлиЭкспресс: что не темнеет и долго служит", "i": "👗", "c": "odezhda-i-stil"}, {"s": "biznes-s-aliekspress-s-chego", "t": "Бизнес с Алиэкспресс с чего начать: полное руководство", "i": "💼", "c": "prodavtsam-i-biznes"}]